[
 {
  "area": "خلدا",
  "area_tier": "راقية",
  "ft": "أرضي",
  "size": 150,
  "advertised_size": 150,
  "internal_size": 150,
  "external_size": "",
  "price_per_sqm_basis": "مساحة القوشان/الداخلية",
  "area_confidence": "deed_area_extracted",
  "area_note": "تم استخراج مساحة داخلية/قوشان من نص الإعلان؛ راجع السند قبل الشراء.",
  "price": 75000,
  "src": "Bayut",
  "title": "شقة أرضية للبيع عرقوب خلدا 150م مدخل مستقل تراس امامى بسعر مميز",
  "url": "https://www.bayut.jo/en/property/details-AH684994.html",
  "ppm": 500,
  "fair": 123600,
  "diff": -39,
  "target": 113712,
  "warn": 0,
  "ev": "🟢 صفقة",
  "phone": "0799999238",
  "advertiser_type": "وسيط / منصة عقارية",
  "contact_note": "تم استخراج رقم الهاتف من صفحة الإعلان الأصلية"
 },
 {
  "area": "أم السماق",
  "area_tier": "راقية",
  "ft": "روف",
  "size": 320,
  "advertised_size": 320,
  "internal_size": "",
  "external_size": "",
  "price_per_sqm_basis": "المساحة المعلنة",
  "area_confidence": "needs_area_verification",
  "area_note": "المساحة قد تشمل روف/ترس/حديقة أو مساحة استعمال؛ يجب تأكيد مساحة القوشان.",
  "price": 175000,
  "src": "Bayut",
  "title": "رووف للبيع في الاردن -عمان - ام السماق مساحه 320م  ",
  "url": "https://www.bayut.jo/en/property/details-elitejo2960.html",
  "ppm": 547,
  "fair": 284800,
  "diff": -39,
  "target": 262016,
  "warn": 0,
  "ev": "🟢 صفقة",
  "phone": "0797020207",
  "advertiser_type": "وسيط / منصة عقارية",
  "contact_note": "تم استخراج رقم الهاتف من صفحة الإعلان الأصلية"
 },
 {
  "area": "دابوق",
  "area_tier": "فاخرة",
  "ft": "روف",
  "size": 330,
  "advertised_size": 330,
  "internal_size": "",
  "external_size": "",
  "price_per_sqm_basis": "المساحة المعلنة",
  "area_confidence": "needs_area_verification",
  "area_note": "المساحة قد تشمل روف/ترس/حديقة أو مساحة استعمال؛ يجب تأكيد مساحة القوشان.",
  "price": 225000,
  "src": "Bayut",
  "title": "روف طابقي مع ترسات للبيع في دابوق، مساحة كلية 330 م",
  "url": "https://www.bayut.jo/en/property/details-HMMS2282.html",
  "ppm": 682,
  "fair": 345510,
  "diff": -35,
  "target": 317869,
  "warn": 0,
  "ev": "🟢 صفقة",
  "phone": "0791235111",
  "advertiser_type": "وسيط / منصة عقارية",
  "contact_note": "تم استخراج رقم الهاتف من صفحة الإعلان الأصلية"
 },
 {
  "area": "خلدا",
  "area_tier": "راقية",
  "ft": "روف",
  "size": 380,
  "advertised_size": 380,
  "internal_size": "",
  "external_size": "",
  "price_per_sqm_basis": "المساحة المعلنة",
  "area_confidence": "needs_area_verification",
  "area_note": "المساحة قد تشمل روف/ترس/حديقة أو مساحة استعمال؛ يجب تأكيد مساحة القوشان.",
  "price": 200000,
  "src": "Bayut",
  "title": "شقة اخير مع روف وترس للبيع في خلدا، مساحة بناء اجمالية 380 م",
  "url": "https://www.bayut.jo/en/property/details-HMMS2408.html",
  "ppm": 526,
  "fair": 300200,
  "diff": -33,
  "target": 276184,
  "warn": 0,
  "ev": "🟢 صفقة",
  "phone": "0791235111",
  "advertiser_type": "وسيط / منصة عقارية",
  "contact_note": "تم استخراج رقم الهاتف من صفحة الإعلان الأصلية"
 },
 {
  "area": "عبدون",
  "area_tier": "فاخرة",
  "ft": "روف",
  "size": 362,
  "advertised_size": 362,
  "internal_size": "",
  "external_size": "",
  "price_per_sqm_basis": "المساحة المعلنة",
  "area_confidence": "needs_area_verification",
  "area_note": "المساحة قد تشمل روف/ترس/حديقة أو مساحة استعمال؛ يجب تأكيد مساحة القوشان.",
  "price": 235000,
  "src": "قوشان",
  "title": "رووف طابقي 3 نوم بأجمل اطلالة في عبدون",
  "url": "https://qoshan.com/property/%d8%b1%d9%88%d9%88%d9%81-%d8%b7%d8%a7%d8%a8%d9%82%d9%8a-3-%d9%86%d9%88%d9%85-%d8%a8%d8%a3%d8%ac%d9%85%d9%84-%d8%a7%d8%b7%d9%84%d8%a7%d9%84%d8%a9-%d9%81%d9%8a-%d8%b9%d8%a8%d8%af%d9%88%d9%86/",
  "ppm": 649,
  "fair": 344624,
  "diff": -32,
  "target": 317054,
  "warn": 0,
  "ev": "🟢 صفقة",
  "phone": "0796868500",
  "advertiser_type": "وسيط / منصة عقارية",
  "contact_note": "تم استخراج رقم الهاتف من صفحة الإعلان الأصلية"
 },
 {
  "area": "دابوق",
  "area_tier": "فاخرة",
  "ft": "روف",
  "size": 336,
  "advertised_size": 336,
  "internal_size": "",
  "external_size": "",
  "price_per_sqm_basis": "المساحة المعلنة",
  "area_confidence": "needs_area_verification",
  "area_note": "المساحة قد تشمل روف/ترس/حديقة أو مساحة استعمال؛ يجب تأكيد مساحة القوشان.",
  "price": 239000,
  "src": "Bayut",
  "title": "شقه طابق اخير مع روف للبيع في الاردن - عمان - دابوق بمساحه 336 متر ",
  "url": "https://www.bayut.jo/en/property/details-elitejo3713.html",
  "ppm": 711,
  "fair": 351792,
  "diff": -32,
  "target": 323649,
  "warn": 0,
  "ev": "🟢 صفقة",
  "phone": "0797020207",
  "advertiser_type": "وسيط / منصة عقارية",
  "contact_note": "تم استخراج رقم الهاتف من صفحة الإعلان الأصلية"
 },
 {
  "area": "طريق المطار",
  "area_tier": "راقية",
  "ft": "روف",
  "size": 310,
  "advertised_size": 310,
  "internal_size": "",
  "external_size": "",
  "price_per_sqm_basis": "المساحة المعلنة",
  "area_confidence": "needs_area_verification",
  "area_note": "المساحة قد تشمل روف/ترس/حديقة أو مساحة استعمال؛ يجب تأكيد مساحة القوشان.",
  "price": 180000,
  "src": "Bayut",
  "title": "طابق ثالث مع روف للبيع في البنيات | الرقم المرجعي:UID000815",
  "url": "https://www.bayut.jo/en/property/details-UID000815.html",
  "ppm": 581,
  "fair": 263190,
  "diff": -32,
  "target": 242135,
  "warn": 0,
  "ev": "🟢 صفقة",
  "phone": "0792058009",
  "advertiser_type": "وسيط / منصة عقارية",
  "contact_note": "تم استخراج رقم الهاتف من صفحة الإعلان الأصلية"
 },
 {
  "area": "دابوق",
  "area_tier": "فاخرة",
  "ft": "أرضي",
  "size": 180,
  "advertised_size": 180,
  "internal_size": "",
  "external_size": "",
  "price_per_sqm_basis": "المساحة المعلنة",
  "area_confidence": "advertised_area_only",
  "area_note": "لم يظهر فصل بين مساحة القوشان والمساحات الخارجية في العنوان.",
  "price": 140000,
  "src": "Bayut",
  "title": "شقه أرضي للبيع في الاردن - عمان - دابوق بمساحه 180م",
  "url": "https://www.bayut.jo/en/property/details-elitejo3997.html",
  "ppm": 778,
  "fair": 193500,
  "diff": -28,
  "target": 178020,
  "warn": 0,
  "ev": "🟢 صفقة",
  "phone": "0797020207",
  "advertiser_type": "وسيط / منصة عقارية",
  "contact_note": "تم استخراج رقم الهاتف من صفحة الإعلان الأصلية"
 },
 {
  "area": "دابوق",
  "area_tier": "فاخرة",
  "ft": "روف",
  "size": 386,
  "advertised_size": 386,
  "internal_size": "",
  "external_size": "",
  "price_per_sqm_basis": "المساحة المعلنة",
  "area_confidence": "needs_area_verification",
  "area_note": "المساحة قد تشمل روف/ترس/حديقة أو مساحة استعمال؛ يجب تأكيد مساحة القوشان.",
  "price": 290000,
  "src": "Bayut",
  "title": "شقه طابق ثالث مميزه مع روف فخم للبيع في دابوق | الرقم المرجعي:UID000241",
  "url": "https://www.bayut.jo/en/property/details-UID000241.html",
  "ppm": 751,
  "fair": 404142,
  "diff": -28,
  "target": 371811,
  "warn": 0,
  "ev": "🟢 صفقة",
  "phone": "0792058009",
  "advertiser_type": "وسيط / منصة عقارية",
  "contact_note": "تم استخراج رقم الهاتف من صفحة الإعلان الأصلية"
 },
 {
  "area": "عبدون",
  "area_tier": "فاخرة",
  "ft": "أرضي",
  "size": 198,
  "advertised_size": 198,
  "internal_size": "",
  "external_size": "",
  "price_per_sqm_basis": "المساحة المعلنة",
  "area_confidence": "needs_area_verification",
  "area_note": "المساحة قد تشمل روف/ترس/حديقة أو مساحة استعمال؛ يجب تأكيد مساحة القوشان.",
  "price": 160000,
  "src": "قوشان",
  "title": "شقة أرضية مع حديقة في عبدون",
  "url": "https://qoshan.com/property/%d8%b4%d9%82%d8%a9-%d8%a3%d8%b1%d8%b6%d9%8a%d8%a9-%d9%85%d8%b9-%d8%ad%d8%af%d9%8a%d9%82%d8%a9-%d9%81%d9%8a-%d8%b9%d8%a8%d8%af%d9%88%d9%86/",
  "ppm": 808,
  "fair": 220374,
  "diff": -27,
  "target": 202744,
  "warn": 0,
  "ev": "✅ عادل-أدنى",
  "phone": "0796868500",
  "advertiser_type": "وسيط / منصة عقارية",
  "contact_note": "تم استخراج رقم الهاتف من صفحة الإعلان الأصلية"
 }
]